explore_cli/__init__.py
explore_cli/main.py
explore_cli-0.4.1.dist-info/METADATA
explore_cli-0.4.1.dist-info/WHEEL
explore_cli-0.4.1.dist-info/entry_points.txt
explore_cli-0.4.1.dist-info/licenses/LICENSE
explore_cli-0.4.1.dist-info/RECORD
