Metadata-Version: 2.4
Name: explore-cli
Version: 0.4.1
Summary: Interactively explore a codebase with an LLM
Author-email: Jeremy Dormitzer <jeremy.dormitzer@gmail.com>
License-File: LICENSE
Requires-Python: >=3.12
Requires-Dist: azure-identity>=1.19.0
Requires-Dist: gnureadline>=8.2.13
Requires-Dist: langchain-chroma>=0.1.4
Requires-Dist: langchain-community>=0.3.14
Requires-Dist: langchain-huggingface>=0.1.2
Requires-Dist: langchain-ollama>=0.2.2
Requires-Dist: langchain-openai>=0.2.14
Requires-Dist: langchain-text-splitters>=0.3.4
Requires-Dist: langchain>=0.3.14
Requires-Dist: pathspec>=0.12.1
Requires-Dist: rich>=13.9.4
